faye_image/__init__.py
faye_image/image_factory.py
faye_image/image_intermediate.py
faye_image/GUI/__init__.py
faye_image/GUI/context.py
faye_image/GUI/core.py
faye_image/GUI/exceptions.py
faye_image/GUI/inputs.py
faye_image/GUI/utils.py
faye_image/GUI/widgets.py
faye_image/GUI/backends/__init__.py
faye_image/GUI/backends/glfw_backend.py
faye_image/builders/__init__.py
faye_image/builders/array_based_builders.py
faye_image/builders/builder_interface.py
faye_image/builders/file_based_builders.py
faye_image/misc/image_resizing.py
faye_image-0.4.1.dist-info/licenses/LICENSE
faye_image-0.4.1.dist-info/METADATA
faye_image-0.4.1.dist-info/WHEEL
faye_image-0.4.1.dist-info/top_level.txt
faye_image-0.4.1.dist-info/RECORD
