Metadata-Version: 2.4
Name: faye-image
Version: 0.4.1
Summary: A image toolkit designed to convert the image file from any supported type to another one with only one line code.
Author-email: Youyang Du <duyouyang957@gmail.com>
License:                                  Apache License
Project-URL: Source Code, https://github.com/icewired-yy/image-toolkit
Project-URL: Bug Tracker, https://github.com/icewired-yy/image-toolkit/issues
Keywords: python,library,image processing
License-File: LICENSE
Requires-Dist: numpy
Requires-Dist: opencv-python
Requires-Dist: imgui[glfw]
Requires-Dist: PyOpenGL
Dynamic: license-file
